a10_nlbaas2oct/__init__.py
a10_nlbaas2oct/a10_config.py
a10_nlbaas2oct/a10_migration.py
a10_nlbaas2oct/a10_nlbaas2oct.conf
a10_nlbaas2oct/db_utils.py
a10_nlbaas2oct/driver.py
a10_nlbaas2oct/flavor_migration.py
a10_nlbaas2oct/lbaas_migration.py
a10_nlbaas2oct-1.3.2.dist-info/DESCRIPTION.rst
a10_nlbaas2oct-1.3.2.dist-info/METADATA
a10_nlbaas2oct-1.3.2.dist-info/RECORD
a10_nlbaas2oct-1.3.2.dist-info/WHEEL
a10_nlbaas2oct-1.3.2.dist-info/entry_points.txt
a10_nlbaas2oct-1.3.2.dist-info/metadata.json
a10_nlbaas2oct-1.3.2.dist-info/pbr.json
a10_nlbaas2oct-1.3.2.dist-info/top_level.txt
