Metadata-Version: 2.0
Name: a10-nlbaas2oct
Version: 1.3.2
Summary: Migrate A10 specific device configs to nlbaas
Home-page: UNKNOWN
Author: Hunter Thompson
Author-email: opensource@a10networks.com
License: Apache-2
Platform: UNKNOWN
Classifier: Development Status :: 3 - Alpha
Classifier: Environment :: OpenStack
Classifier: Intended Audience :: Developers
Classifier: Intended Audience :: Information Technology
Classifier: Intended Audience :: System Administrators
Classifier: License :: OSI Approved :: Apache Software License
Classifier: Operating System :: POSIX :: Linux
Classifier: Programming Language :: Python
Classifier: Programming Language :: Python :: 2.7
Classifier: Programming Language :: Python :: 3
Classifier: Programming Language :: Python :: 3.5
Classifier: Programming Language :: Python :: 3.6
License-File: LICENSE
License-File: AUTHORS
Requires-Dist: oslo.config (>=4.6.0)
Requires-Dist: oslo.db (>=4.27.0)
Requires-Dist: oslo.i18n (>=3.15.3)
Requires-Dist: oslo.log (>=3.30.0)
Requires-Dist: PyMySQL (>=0.7.6)
Requires-Dist: acos-client
